ofxstatement/plugins/__init__.py
ofxstatement/plugins/paypal.py
ofxstatement_paypal_2-3.1.0.dist-info/LICENSE
ofxstatement_paypal_2-3.1.0.dist-info/METADATA
ofxstatement_paypal_2-3.1.0.dist-info/WHEEL
ofxstatement_paypal_2-3.1.0.dist-info/entry_points.txt
ofxstatement_paypal_2-3.1.0.dist-info/top_level.txt
ofxstatement_paypal_2-3.1.0.dist-info/zip-safe
ofxstatement_paypal_2-3.1.0.dist-info/RECORD
