Metadata-Version: 2.2
Name: ofxstatement-paypal-2
Version: 3.1.0
Summary: Plugin for ofxstatement that support conversion from Paypal csv to OFX
Home-page: https://github.com/Alfystar/ofxstatement-paypal.git
Author: Alfystar
Author-email: alfystar1701@gmail.com
License: Apache License 2.0
Keywords: ofx,ofxstatement,paypal
Classifier: Development Status :: 5 - Production/Stable
Classifier: Programming Language :: Python :: 3
Classifier: Natural Language :: English
Classifier: Topic :: Office/Business :: Financial :: Accounting
Classifier: Topic :: Utilities
Classifier: Environment :: Console
Classifier: Operating System :: OS Independent
License-File: LICENSE
Requires-Dist: ofxstatement
Dynamic: author
Dynamic: author-email
Dynamic: classifier
Dynamic: description
Dynamic: description-content-type
Dynamic: home-page
Dynamic: keywords
Dynamic: license
Dynamic: requires-dist
Dynamic: summary
